square_calculator/__init__.py
square_calculator/constants.py
square_calculator/exception_messages.py
square_calculator/square.py
tests/__init__.py
tests/tests.py
square_calculator_library-0.0.2.dist-info/LICENSE
square_calculator_library-0.0.2.dist-info/METADATA
square_calculator_library-0.0.2.dist-info/WHEEL
square_calculator_library-0.0.2.dist-info/top_level.txt
square_calculator_library-0.0.2.dist-info/RECORD
