Metadata-Version: 2.1
Name: square-calculator-library
Version: 0.0.2
Summary: The library allows you to calculate the area of geometric shapes.
Home-page: https://github.com/AVanslov/square_calculator_library
Author: Aleksandr Buchelnikov
Author-email: al.buchelnikov@gmail.com
License: UNKNOWN
Platform: UNKNOWN
Classifier: Programming Language :: Python :: 3.10
Classifier: License :: OSI Approved :: MIT License
Classifier: Operating System :: OS Independent
Requires-Python: >=3.10
License-File: LICENSE
Requires-Dist: flake8-isort (==6.0.0)
Requires-Dist: flake8 (==6.0.0)
Requires-Dist: isort (==5.13.2)
Requires-Dist: mccabe (==0.7.0)
Requires-Dist: pycodestyle (==2.10.0)
Requires-Dist: pyflakes (==3.0.1)
